EFCrud/__init__.py
EFCrud/api_client.py
EFCrud/api_response.py
EFCrud/configuration.py
EFCrud/exceptions.py
EFCrud/py.typed
EFCrud/rest.py
EFCrud/api/__init__.py
EFCrud/api/auth_api.py
EFCrud/api/employees_api.py
EFCrud/api/features_api.py
EFCrud/api/roles_api.py
EFCrud/models/__init__.py
EFCrud/models/employee.py
EFCrud/models/roles.py
EFCrud/models/user.py
EFCrud/models/user_roles.py
EFCrud/models/userdto.py
test/__init__.py
test/test_auth_api.py
test/test_employee.py
test/test_employees_api.py
test/test_features_api.py
test/test_roles.py
test/test_roles_api.py
test/test_user.py
test/test_user_roles.py
test/test_userdto.py
EFCrud-1.0.5.4.dist-info/LICENSE
EFCrud-1.0.5.4.dist-info/METADATA
EFCrud-1.0.5.4.dist-info/WHEEL
EFCrud-1.0.5.4.dist-info/top_level.txt
EFCrud-1.0.5.4.dist-info/RECORD
