Metadata-Version: 2.1
Name: EFCrud
Version: 1.0.5.4
Summary: API client for EFCrud
Home-page: https://github.com/dprakash2101/EFCrudPython/archive/1.0.5.4.tar.gz
Download-URL: https://github.com/dprakash2101/EFCrudPython/archive/1.0.5.4.tar.gz
Author: Devi Prakash
Author-email: dprakash@gmail.com
Project-URL: GitHub Repo, https://github.com/dprakash2101/EFCrudPython
Project-URL: Download, https://github.com/dprakash2101/EFCrudPython/archive/1.0.2.2.tar.gz
Project-URL: Release Notes, https://github.com/dprakash2101/EFCrudPython/releases/tag/1.0.5.4
Classifier: Programming Language :: Python :: 2
Classifier: Programming Language :: Python :: 2.7
Classifier: Programming Language :: Python :: 3
Classifier: Programming Language :: Python :: 3.4
Classifier: Programming Language :: Python :: 3.5
Classifier: Programming Language :: Python :: 3.6
Classifier: Programming Language :: Python :: 3.7
Classifier: Programming Language :: Python :: 3.8
Classifier: Programming Language :: Python :: 3.9
Classifier: License :: OSI Approved :: MIT License
Classifier: Operating System :: OS Independent
License-File: LICENSE
Requires-Dist: requests
